dblocks_core/__init__.py
dblocks_core/config/__init__.py
dblocks_core/config/config.py
dblocks_core/context/__init__.py
dblocks_core/dbi/__init__.py
dblocks_core/dbi/contract.py
dblocks_core/dbi/tera_dbi.py
dblocks_core/deployer/__init__.py
dblocks_core/deployer/deployer.py
dblocks_core/deployer/fsequencer.py
dblocks_core/deployer/tokenizer.py
dblocks_core/exc/__init__.py
dblocks_core/git/__init__.py
dblocks_core/git/git.py
dblocks_core/model/__init__.py
dblocks_core/model/config_model.py
dblocks_core/model/global_converter.py
dblocks_core/model/meta_model.py
dblocks_core/model/plugin_model.py
dblocks_core/packager/__init__.py
dblocks_core/packager/fpackager.py
dblocks_core/parse/__init__.py
dblocks_core/parse/prsr_simple.py
dblocks_core/script/__init__.py
dblocks_core/script/dbe.py
dblocks_core/script/dbexp.py
dblocks_core/script/workflow/__init__.py
dblocks_core/script/workflow/cmd_deployment.py
dblocks_core/script/workflow/cmd_detag.py
dblocks_core/script/workflow/cmd_extraction.py
dblocks_core/script/workflow/cmd_git_copy_changed.py
dblocks_core/script/workflow/cmd_init.py
dblocks_core/script/workflow/cmd_pkg_deployment.py
dblocks_core/script/workflow/cmd_pkg_maint_backup.py
dblocks_core/script/workflow/cmd_quickstart.py
dblocks_core/script/workflow/dbi.py
dblocks_core/tagger/__init__.py
dblocks_core/writer/__init__.py
dblocks_core/writer/contract.py
dblocks_core/writer/fsystem.py
dblocks_plugin/__init__.py
d_blocks_core-0.9.3.40.dist-info/LICENSE
d_blocks_core-0.9.3.40.dist-info/METADATA
d_blocks_core-0.9.3.40.dist-info/WHEEL
d_blocks_core-0.9.3.40.dist-info/entry_points.txt
d_blocks_core-0.9.3.40.dist-info/RECORD
