Metadata-Version: 2.1
Name: d-blocks-core
Version: 0.9.3.40
Summary: 
License: MIT
Author: d-blocks-coder
Author-email: d.blocks.coder@gmail.com
Requires-Python: >=3.10
Classifier: Development Status :: 3 - Alpha
Classifier: Environment :: Console
Classifier: License :: OSI Approved :: MIT License
Classifier: Programming Language :: Python :: 3
Classifier: Programming Language :: Python :: 3.10
Classifier: Programming Language :: Python :: 3.11
Classifier: Programming Language :: Python :: 3.12
Classifier: Topic :: Database
Classifier: Topic :: Software Development
Requires-Dist: attrs (>=24.2.0,<25.0.0)
Requires-Dist: cattrs (>=24.1.2,<25.0.0)
Requires-Dist: click (==8.1.7)
Requires-Dist: loguru (>=0.7.2,<0.8.0)
Requires-Dist: platformdirs (>=4.3.6,<5.0.0)
Requires-Dist: pyaml (>=24.9.0,<25.0.0)
Requires-Dist: rich (>=13.9.4,<14.0.0)
Requires-Dist: sqlalchemy (>=2.0.36,<3.0.0)
Requires-Dist: teradatasql (>=20.0.0.20,<21.0.0.0)
Requires-Dist: teradatasqlalchemy (>=20.0.0.3,<21.0.0.0)
Requires-Dist: typer (>=0.13.1,<0.14.0)
